simkl_mps/__init__.py
simkl_mps/assets/simkl-mps-128.png
simkl_mps/assets/simkl-mps-16.png
simkl_mps/assets/simkl-mps-24.png
simkl_mps/assets/simkl-mps-256.png
simkl_mps/assets/simkl-mps-32.png
simkl_mps/assets/simkl-mps-48.png
simkl_mps/assets/simkl-mps-64.png
simkl_mps/assets/simkl-mps-error.ico
simkl_mps/assets/simkl-mps-error.png
simkl_mps/assets/simkl-mps-paused.ico
simkl_mps/assets/simkl-mps-paused.png
simkl_mps/assets/simkl-mps-running.ico
simkl_mps/assets/simkl-mps-running.png
simkl_mps/assets/simkl-mps-stopped.ico
simkl_mps/assets/simkl-mps-stopped.png
simkl_mps/assets/simkl-mps.ico
simkl_mps/assets/simkl-mps.png
simkl_mps/backlog_cleaner.py
simkl_mps/cli.py
simkl_mps/compatibility_patches.py
simkl_mps/config_manager.py
simkl_mps/credentials.py
simkl_mps/main.py
simkl_mps/media_cache.py
simkl_mps/media_scrobbler.py
simkl_mps/media_tracker.py
simkl_mps/migration.py
simkl_mps/monitor.py
simkl_mps/players/__init__.py
simkl_mps/players/mpc.py
simkl_mps/players/mpcqt.py
simkl_mps/players/mpv.py
simkl_mps/players/mpv_wrappers.py
simkl_mps/players/potplayer.py
simkl_mps/players/vlc.py
simkl_mps/simkl_api.py
simkl_mps/tray_app.py
simkl_mps/tray_base.py
simkl_mps/tray_linux.py
simkl_mps/tray_mac.py
simkl_mps/tray_win.py
simkl_mps/utils/__init__.py
simkl_mps/utils/constants.py
simkl_mps/utils/linux_tray_diagnostics.py
simkl_mps/utils/updater.ps1
simkl_mps/utils/updater.sh
simkl_mps/watch-history-viewer/fonts/Inter-Bold.woff2
simkl_mps/watch-history-viewer/fonts/Inter-Medium.woff2
simkl_mps/watch-history-viewer/fonts/Inter-Regular.woff2
simkl_mps/watch-history-viewer/fonts/Inter-SemiBold.woff2
simkl_mps/watch-history-viewer/fonts.css
simkl_mps/watch-history-viewer/index.html
simkl_mps/watch-history-viewer/script.js
simkl_mps/watch-history-viewer/style.css
simkl_mps/watch_history_manager.py
simkl_mps/window_detection.py
simkl_mps-2.2.1.dist-info/METADATA
simkl_mps-2.2.1.dist-info/WHEEL
simkl_mps-2.2.1.dist-info/entry_points.txt
simkl_mps-2.2.1.dist-info/licenses/LICENSE
simkl_mps-2.2.1.dist-info/RECORD
