Metadata-Version: 2.4
Name: simkl-mps
Version: 2.2.1
Summary: Automatic Media Scrobbler for Simkl
License: GPL-3.0
License-File: LICENSE
Keywords: simkl,scrobbler
Author: kavin
Author-email: kavinthangavel.dev@gmail.com
Requires-Python: >=3.9,<3.14
Classifier: Development Status :: 5 - Production/Stable
Classifier: Intended Audience :: End Users/Desktop
Classifier: License :: OSI Approved :: GNU General Public License v3 (GPLv3)
Classifier: Operating System :: OS Independent
Classifier: Programming Language :: Python :: 3
Classifier: Programming Language :: Python :: 3.9
Classifier: Programming Language :: Python :: 3.10
Classifier: Programming Language :: Python :: 3.11
Classifier: Programming Language :: Python :: 3.12
Classifier: Programming Language :: Python :: 3.13
Provides-Extra: linux
Provides-Extra: linux-full
Provides-Extra: macos
Requires-Dist: PyGObject (>=3.42.0) ; (sys_platform == "linux" and python_version >= "3.9" and python_version < "4.0") and (extra == "linux-full")
Requires-Dist: colorama (>=0.4.4)
Requires-Dist: guessit (>=3.3.0)
Requires-Dist: pillow (>=11.2.0)
Requires-Dist: plyer (>=2.0.0)
Requires-Dist: psutil (>=5.8.0)
Requires-Dist: pygetwindow (>=0.0.9) ; sys_platform == "win32"
Requires-Dist: pyobjc (>=7.3) ; (sys_platform == "darwin") and (extra == "macos")
Requires-Dist: pystray (>=0.19.0)
Requires-Dist: python-dotenv (>=0.15.0)
Requires-Dist: python-xlib (>=0.31) ; (sys_platform == "linux") and (extra == "linux" or extra == "linux-full")
Requires-Dist: pywin32 (>=300) ; sys_platform == "win32"
Requires-Dist: requests (>=2.25.0)
Requires-Dist: winotify (>=1.1.0,<2.0.0) ; sys_platform == "win32"
Project-URL: Bug Reports, https://github.com/ByteTrix/media-player-scrobbler-for-simkl/issues
Project-URL: Documentation, https://github.com/ByteTrix/media-player-scrobbler-for-simkl/wiki
Project-URL: Homepage, https://github.com/ByteTrix/Media-Player-Scrobbler-for-Simkl
Project-URL: Linux System Dependencies, https://github.com/ByteTrix/Media-Player-Scrobbler-for-Simkl/wiki/Installation#linux-installation
Project-URL: Repository, https://github.com/ByteTrix/Media-Player-Scrobbler-for-Simkl
